version-1.0.2/basic/rtl/cores/bin2bcd/bin2bcd.v
module bin2bcd
  #(parameter INPUT_WIDTH = 16,
    parameter DECIMAL_DIGITS = 5)
  (
   input                         i_Clock,
   input [INPUT_WIDTH-1:0]       i_Binary,
   input                         i_Start,
   //
   output [DECIMAL_DIGITS*4-1:0] o_BCD,
   output                        o_DV
   );
   
  parameter s_IDLE              = 3'b000;
  parameter s_SHIFT             = 3'b001;
  parameter s_CHECK_SHIFT_INDEX = 3'b010;
  parameter s_ADD               = 3'b011;
  parameter s_CHECK_DIGIT_INDEX = 3'b100;
  parameter s_BCD_DONE          = 3'b101;

   
  reg [2:0] r_SM_Main = s_IDLE;
   
  // The vector that contains the output BCD
  reg [DECIMAL_DIGITS*4-1:0] r_BCD = 0;
    
  // The vector that contains the input binary value being shifted.
  reg [INPUT_WIDTH-1:0]      r_Binary = 0;
      
  // Keeps track of which Decimal Digit we are indexing
  reg [DECIMAL_DIGITS-1:0]   r_Digit_Index = 0;
    
  // Keeps track of which loop iteration we are on.
  // Number of loops performed = INPUT_WIDTH
  reg [7:0]                  r_Loop_Count = 0;
 
  wire [3:0]                 w_BCD_Digit;
  reg                        r_DV = 1'b0;                       
  reg [4:0] count;

  always @(posedge i_Clock)
    begin
 
      case (r_SM_Main) 
  
        // Stay in this state until i_Start comes along
        s_IDLE :
          begin
            r_DV <= 1'b0;
             
            if (i_Start == 1'b1)
              begin
                r_Binary  <= i_Binary;
                r_SM_Main <= s_SHIFT;
                r_BCD     <= 0;
                count     <= 0;
              end
            else
              r_SM_Main <= s_IDLE;
          end
                 
  
        // Always shift the BCD Vector until we have shifted all bits through
        // Shift the most significant bit of r_Binary into r_BCD lowest bit.
        s_SHIFT :
          begin
            r_BCD     <= r_BCD << 1;
            r_BCD[0]  <= r_Binary[INPUT_WIDTH-1];
            r_Binary  <= r_Binary << 1;
            r_SM_Main <= s_CHECK_SHIFT_INDEX;
          end          
         
  
        // Check if we are done with shifting in r_Binary vector
        s_CHECK_SHIFT_INDEX :
          begin
            if (r_Loop_Count == INPUT_WIDTH-1)
              begin
                r_Loop_Count <= 0;
                r_SM_Main    <= s_BCD_DONE;
              end
            else
              begin
                r_Loop_Count <= r_Loop_Count + 1;
                r_SM_Main    <= s_ADD; 
              end
          end
 
        // Break down each BCD Digit individually. Check them one-by-one to 
        // see if they are greater than 4. If they are, increment by 3. 
        // Put the result back into r_BCD Vector. 
        s_ADD : 
          begin
            if (w_BCD_Digit > 4)
              begin                                     
                r_BCD[(r_Digit_Index*4)+:4] <= w_BCD_Digit + 3;  
              end
             
            r_SM_Main <= s_CHECK_DIGIT_INDEX; 
          end       
         
         
        // Check if we are done incrementing all of the BCD Digits
        s_CHECK_DIGIT_INDEX :
          begin
            if (r_Digit_Index == DECIMAL_DIGITS-1)
              begin
                r_Digit_Index <= 0;
                r_SM_Main     <= s_SHIFT;
              end
            else
              begin
                r_Digit_Index <= r_Digit_Index + 1;
                r_SM_Main     <= s_ADD;
              end
          end
  
  
        //s_BCD_DONE :
        //  begin
        //    r_DV      <= 1'b1;
        //    r_SM_Main <= s_IDLE;
        //  end
        s_BCD_DONE:begin
            r_DV  <= 1'b1;
            count = count + 1;
				    r_SM_Main = (count>29) ? s_IDLE : s_BCD_DONE;
          end         
         
        default :
          r_SM_Main <= s_IDLE;
            
      endcase
    end // always @ (posedge i_Clock)  
 
   
  assign w_BCD_Digit = r_BCD[r_Digit_Index*4 +: 4];
       
  assign o_BCD = r_BCD;
  assign o_DV  = r_DV;
      
endmodule // Binary_to_BCD

version-1.0.2/basic/rtl/cores/bin2bcd/bin2bcd_TB.v
`timescale 1ns / 1ps
`include "/home/kevargaso/Documents/Digital II/version 1.0.2/basic/rtl/cores/bin2bcd/bin2bcd.v"

module bin2bcd_tb;
    // Parámetros del test bench
    parameter INPUT_WIDTH = 16;
    parameter DECIMAL_DIGITS = 5;
    parameter CLK_PERIOD = 25000000; // 10ns = 100MHz
    
    // Señales de entrada
    reg i_Clock;
    reg [INPUT_WIDTH-1:0] i_Binary;
    reg i_Start;
    
    // Señales de salida
    wire [DECIMAL_DIGITS*4-1:0] o_BCD;
    wire o_DV;
    
    // Instancia del módulo bajo prueba
    bin2bcd #(
        .INPUT_WIDTH(INPUT_WIDTH),
        .DECIMAL_DIGITS(DECIMAL_DIGITS)
    )uut (
        .i_Clock(i_Clock),
        .i_Binary(i_Binary),
        .i_Start(i_Start),
        .o_BCD(o_BCD),
        .o_DV(o_DV)
    );
    
    // Generación de reloj
    always #(CLK_PERIOD/2) i_Clock = ~i_Clock;
    
    // Variables para el test bench
    integer i;
    reg [INPUT_WIDTH-1:0] test_values [0:9];
    
    // Inicialización
    initial begin
        // Inicializar valores de prueba
        test_values[0] = 16'd0;      // 0
        test_values[1] = 16'd123;    // 123
        test_values[2] = 16'd999;     // 999
        test_values[3] = 16'd4096;   // 4096
        test_values[4] = 16'd32767;   // 32767
        test_values[5] = 16'd65535;   // 65535
        test_values[6] = 16'd10000;   // 10000
        test_values[7] = 16'd5432;    // 5432
        test_values[8] = 16'd888;     // 888
        test_values[9] = 16'd42;      // 42
        
        // Inicializar señales
        i_Clock = 0;
        i_Binary = 0;
        i_Start = 0;
        
        // Iniciar simulación
        #100;
        
        // Probar varios valores
        for (i = 0; i < 10; i = i + 1) begin
            i_Binary = test_values[i];
            #(CLK_PERIOD*20);
            i_Start = 1;
            #(CLK_PERIOD);
            i_Start = 0;
            
            // Esperar hasta que la conversión esté completa
            wait(o_DV == 1);
            #(CLK_PERIOD*5);
            
            // Mostrar resultados en consola
            $display("Binary: %d -> BCD: %x", i_Binary, o_BCD);
            
            // Pequeña pausa entre pruebas
            #(CLK_PERIOD*10);
        end
        
        // Finalizar simulación
        #100;
        $display("Simulación completada");
        $finish;
    end
    
    // Generar archivo VCD para GTKWave
    initial begin
        $dumpfile("bin2bcd_tb.vcd");
        $dumpvars(0, bin2bcd_tb);
    end
endmodule

version-1.0.2/build/bin2bcd_tb.vcd
$date
	Thu May 22 11:51:54 2025
$end
$version
	Icarus Verilog
$end
$timescale
	1ps
$end
$scope module bin2bcd_tb $end
$var wire 1 ! o_DV $end
$var wire 20 " o_BCD [19:0] $end
$var parameter 32 # CLK_PERIOD $end
$var parameter 32 $ DECIMAL_DIGITS $end
$var parameter 32 % INPUT_WIDTH $end
$var reg 16 & i_Binary [15:0] $end
$var reg 1 ' i_Clock $end
$var reg 1 ( i_Start $end
$var integer 32 ) i [31:0] $end
$scope module uut $end
$var wire 16 * i_Binary [15:0] $end
$var wire 1 ' i_Clock $end
$var wire 1 ( i_Start $end
$var wire 20 + o_BCD [19:0] $end
$var wire 1 ! o_DV $end
$var wire 4 , w_BCD_Digit [3:0] $end
$var parameter 32 - DECIMAL_DIGITS $end
$var parameter 32 . INPUT_WIDTH $end
$var parameter 3 / s_ADD $end
$var parameter 3 0 s_BCD_DONE $end
$var parameter 3 1 s_CHECK_DIGIT_INDEX $end
$var parameter 3 2 s_CHECK_SHIFT_INDEX $end
$var parameter 3 3 s_IDLE $end
$var parameter 3 4 s_SHIFT $end
$var reg 5 5 count [4:0] $end
$var reg 20 6 r_BCD [19:0] $end
$var reg 16 7 r_Binary [15:0] $end
$var reg 1 8 r_DV $end
$var reg 5 9 r_Digit_Index [4:0] $end
$var reg 8 : r_Loop_Count [7:0] $end
$var reg 3 ; r_SM_Main [2:0] $end
$upscope $end
$upscope $end
$enddefinitions $end
$comment Show the parameter values. $end
$dumpall
b1 4
b0 3
b10 2
b100 1
b101 0
b11 /
b10000 .
b101 -
b10000 %
b101 $
b1011111010111100001000000 #
$end
#0
$dumpvars
b0 ;
b0 :
b0 9
08
b0 7
b0 6
bx 5
b0 ,
b0 +
b0 *
bx )
0(
0'
b0 &
b0 "
0!
$end
#100000
b0 )
#12500000000
1'
#25000000000
0'
#37500000000
1'
#50000000000
0'
#62500000000
1'
#75000000000
0'
#87500000000
1'
#100000000000
0'
#112500000000
1'
#125000000000
0'
#137500000000
1'
#150000000000
0'
#162500000000
1'
#175000000000
0'
#187500000000
1'
#200000000000
0'
#212500000000
1'
#225000000000
0'
#237500000000
1'
#250000000000
0'
#262500000000
1'
#275000000000
0'
#287500000000
1'
#300000000000
0'
#312500000000
1'
#325000000000
0'
#337500000000
1'
#350000000000
0'
#362500000000
1'
#375000000000
0'
#387500000000
1'
#400000000000
0'
#412500000000
1'
#425000000000
0'
#437500000000
1'
#450000000000
0'
#462500000000
1'
#475000000000
0'
#487500000000
1'
#500000000000
0'
#500000100000
1(
#512500000000
b0 5
b1 ;
1'
#525000000000
0'
#525000100000
0(
#537500000000
b10 ;
1'
#550000000000
0'
#562500000000
b11 ;
b1 :
1'
#575000000000
0'
#587500000000
b100 ;
1'
#600000000000
0'
#612500000000
b11 ;
b1 9
1'
#625000000000
0'
#637500000000
b100 ;
1'
#650000000000
0'
#662500000000
b11 ;
b10 9
1'
#675000000000
0'
#687500000000
b100 ;
1'
#700000000000
0'
#712500000000
b11 ;
b11 9
1'
#725000000000
0'
#737500000000
b100 ;
1'
#750000000000
0'
#762500000000
b11 ;
b100 9
1'
#775000000000
0'
#787500000000
b100 ;
1'
#800000000000
0'
#812500000000
b1 ;
b0 9
1'
#825000000000
0'
#837500000000
b10 ;
1'
#850000000000
0'
#862500000000
b11 ;
b10 :
1'
#875000000000
0'
#887500000000
b100 ;
1'
#900000000000
0'
#912500000000
b11 ;
b1 9
1'
#925000000000
0'
#937500000000
b100 ;
1'
#950000000000
0'
#962500000000
b11 ;
b10 9
1'
#975000000000
0'
#987500000000
b100 ;
1'
#1000000000000
0'
#1012500000000
b11 ;
b11 9
1'
#1025000000000
0'
#1037500000000
b100 ;
1'
#1050000000000
0'
#1062500000000
b11 ;
b100 9
1'
#1075000000000
0'
#1087500000000
b100 ;
1'
#1100000000000
0'
#1112500000000
b1 ;
b0 9
1'
#1125000000000
0'
#1137500000000
b10 ;
1'
#1150000000000
0'
#1162500000000
b11 ;
b11 :
1'
#1175000000000
0'
#1187500000000
b100 ;
1'
#1200000000000
0'
#1212500000000
b11 ;
b1 9
1'
#1225000000000
0'
#1237500000000
b100 ;
1'
#1250000000000
0'
#1262500000000
b11 ;
b10 9
1'
#1275000000000
0'
#1287500000000
b100 ;
1'
#1300000000000
0'
#1312500000000
b11 ;
b11 9
1'
#1325000000000
0'
#1337500000000
b100 ;
1'
#1350000000000
0'
#1362500000000
b11 ;
b100 9
1'
#1375000000000
0'
#1387500000000
b100 ;
1'
#1400000000000
0'
#1412500000000
b1 ;
b0 9
1'
#1425000000000
0'
#1437500000000
b10 ;
1'
#1450000000000
0'
#1462500000000
b11 ;
b100 :
1'
#1475000000000
0'
#1487500000000
b100 ;
1'
#1500000000000
0'
#1512500000000
b11 ;
b1 9
1'
#1525000000000
0'
#1537500000000
b100 ;
1'
#1550000000000
0'
#1562500000000
b11 ;
b10 9
1'
#1575000000000
0'
#1587500000000
b100 ;
1'
#1600000000000
0'
#1612500000000
b11 ;
b11 9
1'
#1625000000000
0'
#1637500000000
b100 ;
1'
#1650000000000
0'
#1662500000000
b11 ;
b100 9
1'
#1675000000000
0'
#1687500000000
b100 ;
1'
#1700000000000
0'
#1712500000000
b1 ;
b0 9
1'
#1725000000000
0'
#1737500000000
b10 ;
1'
#1750000000000
0'
#1762500000000
b11 ;
b101 :
1'
#1775000000000
0'
#1787500000000
b100 ;
1'
#1800000000000
0'
#1812500000000
b11 ;
b1 9
1'
#1825000000000
0'
#1837500000000
b100 ;
1'
#1850000000000
0'
#1862500000000
b11 ;
b10 9
1'
#1875000000000
0'
#1887500000000
b100 ;
1'
#1900000000000
0'
#1912500000000
b11 ;
b11 9
1'
#1925000000000
0'
#1937500000000
b100 ;
1'
#1950000000000
0'
#1962500000000
b11 ;
b100 9
1'
#1975000000000
0'
#1987500000000
b100 ;
1'
#2000000000000
0'
#2012500000000
b1 ;
b0 9
1'
#2025000000000
0'
#2037500000000
b10 ;
1'
#2050000000000
0'
#2062500000000
b11 ;
b110 :
1'
#2075000000000
0'
#2087500000000
b100 ;
1'
#2100000000000
0'
#2112500000000
b11 ;
b1 9
1'
#2125000000000
0'
#2137500000000
b100 ;
1'
#2150000000000
0'
#2162500000000
b11 ;
b10 9
1'
#2175000000000
0'
#2187500000000
b100 ;
1'
#2200000000000
0'
#2212500000000
b11 ;
b11 9
1'
#2225000000000
0'
#2237500000000
b100 ;
1'
#2250000000000
0'
#2262500000000
b11 ;
b100 9
1'
#2275000000000
0'
#2287500000000
b100 ;
1'
#2300000000000
0'
#2312500000000
b1 ;
b0 9
1'
#2325000000000
0'
#2337500000000
b10 ;
1'
#2350000000000
0'
#2362500000000
b11 ;
b111 :
1'
#2375000000000
0'
#2387500000000
b100 ;
1'
#2400000000000
0'
#2412500000000
b11 ;
b1 9
1'
#2425000000000
0'
#2437500000000
b100 ;
1'
#2450000000000
0'
#2462500000000
b11 ;
b10 9
1'
#2475000000000
0'
#2487500000000
b100 ;
1'
#2500000000000
0'
#2512500000000
b11 ;
b11 9
1'
#2525000000000
0'
#2537500000000
b100 ;
1'
#2550000000000
0'
#2562500000000
b11 ;
b100 9
1'
#2575000000000
0'
#2587500000000
b100 ;
1'
#2600000000000
0'
#2612500000000
b1 ;
b0 9
1'
#2625000000000
0'
#2637500000000
b10 ;
1'
#2650000000000
0'
#2662500000000
b11 ;
b1000 :
1'
#2675000000000
0'
#2687500000000
b100 ;
1'
#2700000000000
0'
#2712500000000
b11 ;
b1 9
1'
#2725000000000
0'
#2737500000000
b100 ;
1'
#2750000000000
0'
#2762500000000
b11 ;
b10 9
1'
#2775000000000
0'
#2787500000000
b100 ;
1'
#2800000000000
0'
#2812500000000
b11 ;
b11 9
1'
#2825000000000
0'
#2837500000000
b100 ;
1'
#2850000000000
0'
#2862500000000
b11 ;
b100 9
1'
#2875000000000
0'
#2887500000000
b100 ;
1'
#2900000000000
0'
#2912500000000
b1 ;
b0 9
1'
#2925000000000
0'
#2937500000000
b10 ;
1'
#2950000000000
0'
#2962500000000
b11 ;
b1001 :
1'
#2975000000000
0'
#2987500000000
b100 ;
1'
#3000000000000
0'
#3012500000000
b11 ;
b1 9
1'
#3025000000000
0'
#3037500000000
b100 ;
1'
#3050000000000
0'
#3062500000000
b11 ;
b10 9
1'
#3075000000000
0'
#3087500000000
b100 ;
1'
#3100000000000
0'
#3112500000000
b11 ;
b11 9
1'
#3125000000000
0'
#3137500000000
b100 ;
1'
#3150000000000
0'
#3162500000000
b11 ;
b100 9
1'
#3175000000000
0'
#3187500000000
b100 ;
1'
#3200000000000
0'
#3212500000000
b1 ;
b0 9
1'
#3225000000000
0'
#3237500000000
b10 ;
1'
#3250000000000
0'
#3262500000000
b11 ;
b1010 :
1'
#3275000000000
0'
#3287500000000
b100 ;
1'
#3300000000000
0'
#3312500000000
b11 ;
b1 9
1'
#3325000000000
0'
#3337500000000
b100 ;
1'
#3350000000000
0'
#3362500000000
b11 ;
b10 9
1'
#3375000000000
0'
#3387500000000
b100 ;
1'
#3400000000000
0'
#3412500000000
b11 ;
b11 9
1'
#3425000000000
0'
#3437500000000
b100 ;
1'
#3450000000000
0'
#3462500000000
b11 ;
b100 9
1'
#3475000000000
0'
#3487500000000
b100 ;
1'
#3500000000000
0'
#3512500000000
b1 ;
b0 9
1'
#3525000000000
0'
#3537500000000
b10 ;
1'
#3550000000000
0'
#3562500000000
b11 ;
b1011 :
1'
#3575000000000
0'
#3587500000000
b100 ;
1'
#3600000000000
0'
#3612500000000
b11 ;
b1 9
1'
#3625000000000
0'
#3637500000000
b100 ;
1'
#3650000000000
0'
#3662500000000
b11 ;
b10 9
1'
#3675000000000
0'
#3687500000000
b100 ;
1'
#3700000000000
0'
#3712500000000
b11 ;
b11 9
1'
#3725000000000
0'
#3737500000000
b100 ;
1'
#3750000000000
0'
#3762500000000
b11 ;
b100 9
1'
#3775000000000
0'
#3787500000000
b100 ;
1'
#3800000000000
0'
#3812500000000
b1 ;
b0 9
1'
#3825000000000
0'
#3837500000000
b10 ;
1'
#3850000000000
0'
#3862500000000
b11 ;
b1100 :
1'
#3875000000000
0'
#3887500000000
b100 ;
1'
#3900000000000
0'
#3912500000000
b11 ;
b1 9
1'
#3925000000000
0'
#3937500000000
b100 ;
1'
#3950000000000
0'
#3962500000000
b11 ;
b10 9
1'
#3975000000000
0'
#3987500000000
b100 ;
1'
#4000000000000
0'
#4012500000000
b11 ;
b11 9
1'
#4025000000000
0'
#4037500000000
b100 ;
1'
#4050000000000
0'
#4062500000000
b11 ;
b100 9
1'
#4075000000000
0'
#4087500000000
b100 ;
1'
#4100000000000
0'
#4112500000000
b1 ;
b0 9
1'
#4125000000000
0'
#4137500000000
b10 ;
1'
#4150000000000
0'
#4162500000000
b11 ;
b1101 :
1'
#4175000000000
0'
#4187500000000
b100 ;
1'
#4200000000000
0'
#4212500000000
b11 ;
b1 9
1'
#4225000000000
0'
#4237500000000
b100 ;
1'
#4250000000000
0'
#4262500000000
b11 ;
b10 9
1'
#4275000000000
0'
#4287500000000
b100 ;
1'
#4300000000000
0'
#4312500000000
b11 ;
b11 9
1'
#4325000000000
0'
#4337500000000
b100 ;
1'
#4350000000000
0'
#4362500000000
b11 ;
b100 9
1'
#4375000000000
0'
#4387500000000
b100 ;
1'
#4400000000000
0'
#4412500000000
b1 ;
b0 9
1'
#4425000000000
0'
#4437500000000
b10 ;
1'
#4450000000000
0'
#4462500000000
b11 ;
b1110 :
1'
#4475000000000
0'
#4487500000000
b100 ;
1'
#4500000000000
0'
#4512500000000
b11 ;
b1 9
1'
#4525000000000
0'
#4537500000000
b100 ;
1'
#4550000000000
0'
#4562500000000
b11 ;
b10 9
1'
#4575000000000
0'
#4587500000000
b100 ;
1'
#4600000000000
0'
#4612500000000
b11 ;
b11 9
1'
#4625000000000
0'
#4637500000000
b100 ;
1'
#4650000000000
0'
#4662500000000
b11 ;
b100 9
1'
#4675000000000
0'
#4687500000000
b100 ;
1'
#4700000000000
0'
#4712500000000
b1 ;
b0 9
1'
#4725000000000
0'
#4737500000000
b10 ;
1'
#4750000000000
0'
#4762500000000
b11 ;
b1111 :
1'
#4775000000000
0'
#4787500000000
b100 ;
1'
#4800000000000
0'
#4812500000000
b11 ;
b1 9
1'
#4825000000000
0'
#4837500000000
b100 ;
1'
#4850000000000
0'
#4862500000000
b11 ;
b10 9
1'
#4875000000000
0'
#4887500000000
b100 ;
1'
#4900000000000
0'
#4912500000000
b11 ;
b11 9
1'
#4925000000000
0'
#4937500000000
b100 ;
1'
#4950000000000
0'
#4962500000000
b11 ;
b100 9
1'
#4975000000000
0'
#4987500000000
b100 ;
1'
#5000000000000
0'
#5012500000000
b1 ;
b0 9
1'
#5025000000000
0'
#5037500000000
b10 ;
1'
#5050000000000
0'
#5062500000000
b101 ;
b0 :
1'
#5075000000000
0'
#5087500000000
1!
18
b1 5
1'
#5100000000000
0'
#5112500000000
b10 5
1'
#5125000000000
0'
#5137500000000
b11 5
1'
#5150000000000
0'
#5162500000000
b100 5
1'
#5175000000000
0'
#5187500000000
b101 5
1'
#5200000000000
0'
#5212500000000
b110 5
1'
#5225000000000
0'
#5237500000000
b111 5
1'
#5250000000000
0'
#5262500000000
b1000 5
1'
#5275000000000
0'
#5287500000000
b1001 5
1'
#5300000000000
0'
#5312500000000
b1010 5
1'
#5325000000000
0'
#5337500000000
b1011 5
1'
#5350000000000
0'
#5362500000000
b1100 5
1'
#5375000000000
0'
#5387500000000
b1101 5
1'
#5400000000000
0'
#5412500000000
b1110 5
1'
#5425000000000
0'
#5437500000000
b1111 5
1'
#5450000000000
0'
#5462500000000
b10000 5
1'
b1111011 &
b1111011 *
b1 )
#5475000000000
0'
#5487500000000
b10001 5
1'
#5500000000000
0'
#5512500000000
b10010 5
1'
#5525000000000
0'
#5537500000000
b10011 5
1'
#5550000000000
0'
#5562500000000
b10100 5
1'
#5575000000000
0'
#5587500000000
b10101 5
1'
#5600000000000
0'
#5612500000000
b10110 5
1'
#5625000000000
0'
#5637500000000
b10111 5
1'
#5650000000000
0'
#5662500000000
b11000 5
1'
#5675000000000
0'
#5687500000000
b11001 5
1'
#5700000000000
0'
#5712500000000
b11010 5
1'
#5725000000000
0'
#5737500000000
b11011 5
1'
#5750000000000
0'
#5762500000000
b11100 5
1'
#5775000000000
0'
#5787500000000
b11101 5
1'
#5800000000000
0'
#5812500000000
b0 ;
b11110 5
1'
#5825000000000
0'
#5837500000000
0!
08
1'
#5850000000000
0'
#5862500000000
1'
#5875000000000
0'
#5887500000000
1'
#5900000000000
0'
#5912500000000
1'
#5925000000000
0'
#5937500000000
1'
#5950000000000
0'
#5962500000000
b0 5
b1 ;
b1111011 7
1'
1(
#5975000000000
0'
#5987500000000
b10 ;
b11110110 7
1'
0(
#6000000000000
0'
#6012500000000
b11 ;
b1 :
1'
#6025000000000
0'
#6037500000000
b100 ;
1'
#6050000000000
0'
#6062500000000
b11 ;
b1 9
1'
#6075000000000
0'
#6087500000000
b100 ;
1'
#6100000000000
0'
#6112500000000
b11 ;
b10 9
1'
#6125000000000
0'
#6137500000000
b100 ;
1'
#6150000000000
0'
#6162500000000
b11 ;
b11 9
1'
#6175000000000
0'
#6187500000000
b100 ;
1'
#6200000000000
0'
#6212500000000
b11 ;
b100 9
1'
#6225000000000
0'
#6237500000000
b100 ;
1'
#6250000000000
0'
#6262500000000
b1 ;
b0 9
1'
#6275000000000
0'
#6287500000000
b10 ;
b111101100 7
1'
#6300000000000
0'
#6312500000000
b11 ;
b10 :
1'
#6325000000000
0'
#6337500000000
b100 ;
1'
#6350000000000
0'
#6362500000000
b11 ;
b1 9
1'
#6375000000000
0'
#6387500000000
b100 ;
1'
#6400000000000
0'
#6412500000000
b11 ;
b10 9
1'
#6425000000000
0'
#6437500000000
b100 ;
1'
#6450000000000
0'
#6462500000000
b11 ;
b11 9
1'
#6475000000000
0'
#6487500000000
b100 ;
1'
#6500000000000
0'
#6512500000000
b11 ;
b100 9
1'
#6525000000000
0'
#6537500000000
b100 ;
1'
#6550000000000
0'
#6562500000000
b1 ;
b0 9
1'
#6575000000000
0'
#6587500000000
b10 ;
b1111011000 7
1'
#6600000000000
0'
#6612500000000
b11 ;
b11 :
1'
#6625000000000
0'
#6637500000000
b100 ;
1'
#6650000000000
0'
#6662500000000
b11 ;
b1 9
1'
#6675000000000
0'
#6687500000000
b100 ;
1'
#6700000000000
0'
#6712500000000
b11 ;
b10 9
1'
#6725000000000
0'
#6737500000000
b100 ;
1'
#6750000000000
0'
#6762500000000
b11 ;
b11 9
1'
#6775000000000
0'
#6787500000000
b100 ;
1'
#6800000000000
0'
#6812500000000
b11 ;
b100 9
1'
#6825000000000
0'
#6837500000000
b100 ;
1'
#6850000000000
0'
#6862500000000
b1 ;
b0 9
1'
#6875000000000
0'
#6887500000000
b10 ;
b11110110000 7
1'
#6900000000000
0'
#6912500000000
b11 ;
b100 :
1'
#6925000000000
0'
#6937500000000
b100 ;
1'
#6950000000000
0'
#6962500000000
b11 ;
b1 9
1'
#6975000000000
0'
#6987500000000
b100 ;
1'
#7000000000000
0'
#7012500000000
b11 ;
b10 9
1'
#7025000000000
0'
#7037500000000
b100 ;
1'
#7050000000000
0'
#7062500000000
b11 ;
b11 9
1'
#7075000000000
0'
#7087500000000
b100 ;
1'
#7100000000000
0'
#7112500000000
b11 ;
b100 9
1'
#7125000000000
0'
#7137500000000
b100 ;
1'
#7150000000000
0'
#7162500000000
b1 ;
b0 9
1'
#7175000000000
0'
#7187500000000
b10 ;
b111101100000 7
1'
#7200000000000
0'
#7212500000000
b11 ;
b101 :
1'
#7225000000000
0'
#7237500000000
b100 ;
1'
#7250000000000
0'
#7262500000000
b11 ;
b1 9
1'
#7275000000000
0'
#7287500000000
b100 ;
1'
#7300000000000
0'
#7312500000000
b11 ;
b10 9
1'
#7325000000000
0'
#7337500000000
b100 ;
1'
#7350000000000
0'
#7362500000000
b11 ;
b11 9
1'
#7375000000000
0'
#7387500000000
b100 ;
1'
#7400000000000
0'
#7412500000000
b11 ;
b100 9
1'
#7425000000000
0'
#7437500000000
b100 ;
1'
#7450000000000
0'
#7462500000000
b1 ;
b0 9
1'
#7475000000000
0'
#7487500000000
b10 ;
b1111011000000 7
1'
#7500000000000
0'
#7512500000000
b11 ;
b110 :
1'
#7525000000000
0'
#7537500000000
b100 ;
1'
#7550000000000
0'
#7562500000000
b11 ;
b1 9
1'
#7575000000000
0'
#7587500000000
b100 ;
1'
#7600000000000
0'
#7612500000000
b11 ;
b10 9
1'
#7625000000000
0'
#7637500000000
b100 ;
1'
#7650000000000
0'
#7662500000000
b11 ;
b11 9
1'
#7675000000000
0'
#7687500000000
b100 ;
1'
#7700000000000
0'
#7712500000000
b11 ;
b100 9
1'
#7725000000000
0'
#7737500000000
b100 ;
1'
#7750000000000
0'
#7762500000000
b1 ;
b0 9
1'
#7775000000000
0'
#7787500000000
b10 ;
b11110110000000 7
1'
#7800000000000
0'
#7812500000000
b11 ;
b111 :
1'
#7825000000000
0'
#7837500000000
b100 ;
1'
#7850000000000
0'
#7862500000000
b11 ;
b1 9
1'
#7875000000000
0'
#7887500000000
b100 ;
1'
#7900000000000
0'
#7912500000000
b11 ;
b10 9
1'
#7925000000000
0'
#7937500000000
b100 ;
1'
#7950000000000
0'
#7962500000000
b11 ;
b11 9
1'
#7975000000000
0'
#7987500000000
b100 ;
1'
#8000000000000
0'
#8012500000000
b11 ;
b100 9
1'
#8025000000000
0'
#8037500000000
b100 ;
1'
#8050000000000
0'
#8062500000000
b1 ;
b0 9
1'
#8075000000000
0'
#8087500000000
b10 ;
b111101100000000 7
1'
#8100000000000
0'
#8112500000000
b11 ;
b1000 :
1'
#8125000000000
0'
#8137500000000
b100 ;
1'
#8150000000000
0'
#8162500000000
b11 ;
b1 9
1'
#8175000000000
0'
#8187500000000
b100 ;
1'
#8200000000000
0'
#8212500000000
b11 ;
b10 9
1'
#8225000000000
0'
#8237500000000
b100 ;
1'
#8250000000000
0'
#8262500000000
b11 ;
b11 9
1'
#8275000000000
0'
#8287500000000
b100 ;
1'
#8300000000000
0'
#8312500000000
b11 ;
b100 9
1'
#8325000000000
0'
#8337500000000
b100 ;
1'
#8350000000000
0'
#8362500000000
b1 ;
b0 9
1'
#8375000000000
0'
#8387500000000
b10 ;
b1111011000000000 7
1'
#8400000000000
0'
#8412500000000
b11 ;
b1001 :
1'
#8425000000000
0'
#8437500000000
b100 ;
1'
#8450000000000
0'
#8462500000000
b11 ;
b1 9
1'
#8475000000000
0'
#8487500000000
b100 ;
1'
#8500000000000
0'
#8512500000000
b11 ;
b10 9
1'
#8525000000000
0'
#8537500000000
b100 ;
1'
#8550000000000
0'
#8562500000000
b11 ;
b11 9
1'
#8575000000000
0'
#8587500000000
b100 ;
1'
#8600000000000
0'
#8612500000000
b11 ;
b100 9
1'
#8625000000000
0'
#8637500000000
b100 ;
1'
#8650000000000
0'
#8662500000000
b1 ;
b0 9
1'
#8675000000000
0'
#8687500000000
b10 ;
b1110110000000000 7
b1 ,
b1 "
b1 +
b1 6
1'
#8700000000000
0'
#8712500000000
b11 ;
b1010 :
1'
#8725000000000
0'
#8737500000000
b100 ;
1'
#8750000000000
0'
#8762500000000
b11 ;
b0 ,
b1 9
1'
#8775000000000
0'
#8787500000000
b100 ;
1'
#8800000000000
0'
#8812500000000
b11 ;
b10 9
1'
#8825000000000
0'
#8837500000000
b100 ;
1'
#8850000000000
0'
#8862500000000
b11 ;
b11 9
1'
#8875000000000
0'
#8887500000000
b100 ;
1'
#8900000000000
0'
#8912500000000
b11 ;
b100 9
1'
#8925000000000
0'
#8937500000000
b100 ;
1'
#8950000000000
0'
#8962500000000
b1 ;
b1 ,
b0 9
1'
#8975000000000
0'
#8987500000000
b10 ;
b1101100000000000 7
b11 ,
b11 "
b11 +
b11 6
1'
#9000000000000
0'
#9012500000000
b11 ;
b1011 :
1'
#9025000000000
0'
#9037500000000
b100 ;
1'
#9050000000000
0'
#9062500000000
b11 ;
b0 ,
b1 9
1'
#9075000000000
0'
#9087500000000
b100 ;
1'
#9100000000000
0'
#9112500000000
b11 ;
b10 9
1'
#9125000000000
0'
#9137500000000
b100 ;
1'
#9150000000000
0'
#9162500000000
b11 ;
b11 9
1'
#9175000000000
0'
#9187500000000
b100 ;
1'
#9200000000000
0'
#9212500000000
b11 ;
b100 9
1'
#9225000000000
0'
#9237500000000
b100 ;
1'
#9250000000000
0'
#9262500000000
b1 ;
b11 ,
b0 9
1'
#9275000000000
0'
#9287500000000
b10 ;
b1011000000000000 7
b111 ,
b111 "
b111 +
b111 6
1'
#9300000000000
0'
#9312500000000
b11 ;
b1100 :
1'
#9325000000000
0'
#9337500000000
b100 ;
b1010 ,
b1010 "
b1010 +
b1010 6
1'
#9350000000000
0'
#9362500000000
b11 ;
b0 ,
b1 9
1'
#9375000000000
0'
#9387500000000
b100 ;
1'
#9400000000000
0'
#9412500000000
b11 ;
b10 9
1'
#9425000000000
0'
#9437500000000
b100 ;
1'
#9450000000000
0'
#9462500000000
b11 ;
b11 9
1'
#9475000000000
0'
#9487500000000
b100 ;
1'
#9500000000000
0'
#9512500000000
b11 ;
b100 9
1'
#9525000000000
0'
#9537500000000
b100 ;
1'
#9550000000000
0'
#9562500000000
b1 ;
b1010 ,
b0 9
1'
#9575000000000
0'
#9587500000000
b10 ;
b110000000000000 7
b101 ,
b10101 "
b10101 +
b10101 6
1'
#9600000000000
0'
#9612500000000
b11 ;
b1101 :
1'
#9625000000000
0'
#9637500000000
b100 ;
b1000 ,
b11000 "
b11000 +
b11000 6
1'
#9650000000000
0'
#9662500000000
b11 ;
b1 ,
b1 9
1'
#9675000000000
0'
#9687500000000
b100 ;
1'
#9700000000000
0'
